harvest_invoice/__init__.py
harvest_invoice/command_line.py
harvest_invoice/invoice.py
harvest_invoice-0.0.1.dist-info/DESCRIPTION.rst
harvest_invoice-0.0.1.dist-info/METADATA
harvest_invoice-0.0.1.dist-info/RECORD
harvest_invoice-0.0.1.dist-info/WHEEL
harvest_invoice-0.0.1.dist-info/entry_points.txt
harvest_invoice-0.0.1.dist-info/metadata.json
harvest_invoice-0.0.1.dist-info/top_level.txt
